ostk/__init__.py
ostk/astrodynamics/OpenSpaceToolkitAstrodynamicsPy.cpython-312-aarch64-linux-gnu.so
ostk/astrodynamics/__init__.py
ostk/astrodynamics/__init__.pyi
ostk/astrodynamics/access.pyi
ostk/astrodynamics/converters.py
ostk/astrodynamics/converters.pyi
ostk/astrodynamics/dataframe.py
ostk/astrodynamics/display.py
ostk/astrodynamics/dynamics.pyi
ostk/astrodynamics/eclipse.pyi
ostk/astrodynamics/estimator.pyi
ostk/astrodynamics/event_condition.pyi
ostk/astrodynamics/guidance_law.pyi
ostk/astrodynamics/libopen-space-toolkit-astrodynamics.so.17
ostk/astrodynamics/solver.pyi
ostk/astrodynamics/utilities.py
ostk/astrodynamics/viewer.py
ostk/astrodynamics/conjunction/__init__.pyi
ostk/astrodynamics/conjunction/close_approach.pyi
ostk/astrodynamics/conjunction/message/__init__.pyi
ostk/astrodynamics/conjunction/message/ccsds.pyi
ostk/astrodynamics/data/__init__.pyi
ostk/astrodynamics/data/provider.pyi
ostk/astrodynamics/flight/__init__.pyi
ostk/astrodynamics/flight/system.pyi
ostk/astrodynamics/flight/profile/__init__.pyi
ostk/astrodynamics/flight/profile/model.pyi
ostk/astrodynamics/pytrajectory/__init__.py
ostk/astrodynamics/pytrajectory/__init__.pyi
ostk/astrodynamics/pytrajectory/pystate.py
ostk/astrodynamics/pytrajectory/pystate.pyi
ostk/astrodynamics/test/__init__.py
ostk/astrodynamics/test/conftest.py
ostk/astrodynamics/test/test_access.py
ostk/astrodynamics/test/test_converters.py
ostk/astrodynamics/test/test_dataframe.py
ostk/astrodynamics/test/test_display.py
ostk/astrodynamics/test/test_event_condition.py
ostk/astrodynamics/test/test_import.py
ostk/astrodynamics/test/test_root_solver.py
ostk/astrodynamics/test/test_trajectory.py
ostk/astrodynamics/test/test_utilities.py
ostk/astrodynamics/test/test_viewer.py
ostk/astrodynamics/test/access/__init__.py
ostk/astrodynamics/test/access/test_generator.py
ostk/astrodynamics/test/access/test_visibility_criterion.py
ostk/astrodynamics/test/conjunction/test_close_approach.py
open_space_toolkit_astrodynamics-17.3.3.dist-info/METADATA
open_space_toolkit_astrodynamics-17.3.3.dist-info/WHEEL
open_space_toolkit_astrodynamics-17.3.3.dist-info/top_level.txt
open_space_toolkit_astrodynamics-17.3.3.dist-info/zip-safe
open_space_toolkit_astrodynamics-17.3.3.dist-info/RECORD
